_aegis_game/__init__.py
_aegis_game/aegis_config.py
_aegis_game/agent.py
_aegis_game/agent_controller.py
_aegis_game/agent_type.py
_aegis_game/args_parser.py
_aegis_game/cli.py
_aegis_game/constants.py
_aegis_game/decorator.py
_aegis_game/game.py
_aegis_game/game_pb.py
_aegis_game/id_gen.py
_aegis_game/logger.py
_aegis_game/message.py
_aegis_game/message_buffer.py
_aegis_game/play.py
_aegis_game/py.typed
_aegis_game/server_websocket.py
_aegis_game/team.py
_aegis_game/team_info.py
_aegis_game/world.py
_aegis_game/world_pb.py
_aegis_game/agent_predictions/__init__.py
_aegis_game/agent_predictions/data_loader.py
_aegis_game/agent_predictions/prediction_handler.py
_aegis_game/cli_scripts/__init__.py
_aegis_game/cli_scripts/build_public_api.py
_aegis_game/cli_scripts/client_installer.py
_aegis_game/cli_scripts/init_scaffold.py
_aegis_game/cli_scripts/update_client.py
_aegis_game/cli_scripts/version_checker.py
_aegis_game/common/__init__.py
_aegis_game/common/cell.py
_aegis_game/common/cell_info.py
_aegis_game/common/direction.py
_aegis_game/common/location.py
_aegis_game/common/objects/__init__.py
_aegis_game/common/objects/rubble.py
_aegis_game/common/objects/survivor.py
_aegis_game/common/objects/world_object.py
_aegis_game/sandbox/__init__.py
_aegis_game/sandbox/core.py
_aegis_game/sandbox/sandbox.py
_aegis_game/sandbox/typed_ast.py
_aegis_game/schemas/cell_pb2.py
_aegis_game/schemas/cell_pb2.pyi
_aegis_game/schemas/event_pb2.py
_aegis_game/schemas/event_pb2.pyi
_aegis_game/schemas/game_pb2.py
_aegis_game/schemas/game_pb2.pyi
_aegis_game/schemas/location_pb2.py
_aegis_game/schemas/location_pb2.pyi
_aegis_game/schemas/spawn_pb2.py
_aegis_game/schemas/spawn_pb2.pyi
_aegis_game/schemas/team_pb2.py
_aegis_game/schemas/team_pb2.pyi
_aegis_game/schemas/turn_pb2.py
_aegis_game/schemas/turn_pb2.pyi
_aegis_game/schemas/world_object_pb2.py
_aegis_game/schemas/world_object_pb2.pyi
_aegis_game/schemas/world_pb2.py
_aegis_game/schemas/world_pb2.pyi
aegis_game-2.9.8.dist-info/METADATA
aegis_game-2.9.8.dist-info/WHEEL
aegis_game-2.9.8.dist-info/entry_points.txt
aegis_game-2.9.8.dist-info/licenses/LICENSE.md
aegis_game-2.9.8.dist-info/RECORD
