Metadata-Version: 2.4
Name: aegis-game
Version: 2.9.8
Summary: Survivor Simulation Game
Project-URL: Documentation, https://aegis-game.github.io/aegis-docs/
Project-URL: Repository, https://github.com/AEGIS-GAME/aegis
License-File: LICENSE.md
Requires-Python: >=3.12
Requires-Dist: numpy>=2.1.3
Requires-Dist: packaging>=25.0
Requires-Dist: protobuf>=6.32.0
Requires-Dist: pyyaml>=6.0.2
Requires-Dist: requests>=2.32.4
Requires-Dist: restrictedpython>=8.0
Requires-Dist: websocket-server==0.6.4
